phone_mcp/__init__.py
phone_mcp/__main__.py
phone_mcp/cli.py
phone_mcp/config.py
phone_mcp/core.py
phone_mcp/tools/__init__.py
phone_mcp/tools/apps.py
phone_mcp/tools/call.py
phone_mcp/tools/contacts.py
phone_mcp/tools/interactions.py
phone_mcp/tools/maps.py
phone_mcp/tools/media.py
phone_mcp/tools/messaging.py
phone_mcp/tools/screen_interface.py
phone_mcp/tools/system.py
phone_mcp/tools/ui.py
phone_mcp/tools/ui_enhanced.py
phone_mcp/tools/ui_monitor.py
phone_mcp-0.3.6.dist-info/licenses/LICENSE
phone_mcp-0.3.6.dist-info/METADATA
phone_mcp-0.3.6.dist-info/WHEEL
phone_mcp-0.3.6.dist-info/entry_points.txt
phone_mcp-0.3.6.dist-info/top_level.txt
phone_mcp-0.3.6.dist-info/RECORD
