Metadata-Version: 2.4
Name: phone-mcp
Version: 0.3.6
Summary: A phone control plugin for MCP that allows you to control your Android phone through ADB commands to connect any human
Home-page: https://github.com/hao-cyber/phone-mcp
Author: hao
Author-email: hao@hao.com
License: Apache-2.0
Keywords: mcp,phone,android,adb
Classifier: Programming Language :: Python :: 3
Classifier: License :: OSI Approved :: Apache Software License
Classifier: Operating System :: OS Independent
Requires-Python: >=3.7
License-File: LICENSE
Requires-Dist: mcp>=1.6.0
Requires-Dist: aiohttp>=3.8.0
Requires-Dist: asyncio>=3.4.3
Requires-Dist: pypinyin>=0.54.0
Dynamic: author
Dynamic: author-email
Dynamic: classifier
Dynamic: description
Dynamic: description-content-type
Dynamic: home-page
Dynamic: keywords
Dynamic: license-file
Dynamic: requires-dist
Dynamic: requires-python
Dynamic: summary
